awslabs/__init__.py
awslabs/cloudwatch_applicationsignals_mcp_server/__init__.py
awslabs/cloudwatch_applicationsignals_mcp_server/audit_presentation_utils.py
awslabs/cloudwatch_applicationsignals_mcp_server/audit_utils.py
awslabs/cloudwatch_applicationsignals_mcp_server/aws_clients.py
awslabs/cloudwatch_applicationsignals_mcp_server/canary_utils.py
awslabs/cloudwatch_applicationsignals_mcp_server/change_tools.py
awslabs/cloudwatch_applicationsignals_mcp_server/enablement_tools.py
awslabs/cloudwatch_applicationsignals_mcp_server/server.py
awslabs/cloudwatch_applicationsignals_mcp_server/service_audit_utils.py
awslabs/cloudwatch_applicationsignals_mcp_server/service_tools.py
awslabs/cloudwatch_applicationsignals_mcp_server/sli_report_client.py
awslabs/cloudwatch_applicationsignals_mcp_server/slo_tools.py
awslabs/cloudwatch_applicationsignals_mcp_server/trace_tools.py
awslabs/cloudwatch_applicationsignals_mcp_server/utils.py
awslabs/cloudwatch_applicationsignals_mcp_server/enablement_guides/templates/ec2/ec2-dotnet-enablement.md
awslabs/cloudwatch_applicationsignals_mcp_server/enablement_guides/templates/ec2/ec2-java-enablement.md
awslabs/cloudwatch_applicationsignals_mcp_server/enablement_guides/templates/ec2/ec2-nodejs-enablement.md
awslabs/cloudwatch_applicationsignals_mcp_server/enablement_guides/templates/ec2/ec2-python-enablement.md
awslabs/cloudwatch_applicationsignals_mcp_server/enablement_guides/templates/ecs/ecs-dotnet-enablement.md
awslabs/cloudwatch_applicationsignals_mcp_server/enablement_guides/templates/ecs/ecs-java-enablement.md
awslabs/cloudwatch_applicationsignals_mcp_server/enablement_guides/templates/ecs/ecs-nodejs-enablement.md
awslabs/cloudwatch_applicationsignals_mcp_server/enablement_guides/templates/ecs/ecs-python-enablement.md
awslabs/cloudwatch_applicationsignals_mcp_server/enablement_guides/templates/eks/eks-dotnet-enablement.md
awslabs/cloudwatch_applicationsignals_mcp_server/enablement_guides/templates/eks/eks-java-enablement.md
awslabs_cloudwatch_applicationsignals_mcp_server-0.1.25.dist-info/METADATA
awslabs_cloudwatch_applicationsignals_mcp_server-0.1.25.dist-info/WHEEL
awslabs_cloudwatch_applicationsignals_mcp_server-0.1.25.dist-info/entry_points.txt
awslabs_cloudwatch_applicationsignals_mcp_server-0.1.25.dist-info/licenses/LICENSE
awslabs_cloudwatch_applicationsignals_mcp_server-0.1.25.dist-info/licenses/NOTICE
awslabs_cloudwatch_applicationsignals_mcp_server-0.1.25.dist-info/RECORD
