Metadata-Version: 2.4
Name: awslabs.cloudwatch-applicationsignals-mcp-server
Version: 0.1.25
Summary: An AWS Labs Model Context Protocol (MCP) server for AWS Application Signals
Project-URL: Homepage, https://awslabs.github.io/mcp/
Project-URL: Documentation, https://awslabs.github.io/mcp/servers/cloudwatch-applicationsignals-mcp-server/
Project-URL: Source, https://github.com/awslabs/mcp.git
Project-URL: Bug Tracker, https://github.com/awslabs/mcp/issues
Project-URL: Changelog, https://github.com/awslabs/mcp/blob/main/src/cloudwatch-applicationsignals-mcp-server/CHANGELOG.md
Author: Amazon Web Services
Author-email: AWSLabs MCP <203918161+awslabs-mcp@users.noreply.github.com>
License: Apache-2.0
License-File: LICENSE
License-File: NOTICE
Classifier: License :: OSI Approved :: Apache Software License
Classifier: Operating System :: OS Independent
Classifier: Programming Language :: Python
Classifier: Programming Language :: Python :: 3
Classifier: Programming Language :: Python :: 3.10
Classifier: Programming Language :: Python :: 3.11
Classifier: Programming Language :: Python :: 3.12
Classifier: Programming Language :: Python :: 3.13
Requires-Python: >=3.10
Requires-Dist: boto3>=1.42.0
Requires-Dist: httpx>=0.24.0
Requires-Dist: loguru>=0.7.3
Requires-Dist: mcp[cli]>=1.23.0
Requires-Dist: pydantic>=2.11.1
